pagic/__init__.py
pagic/cli.py
pagic/html.py
pagic/macros.py
pagic/menus.py
pagic/page.py
pagic/pagic.py
pagic/routing.py
pagic/scanner.py
pagic/types.py
pagic/view_model.py
pagic-0.2.2.dist-info/LICENSE
pagic-0.2.2.dist-info/WHEEL
pagic-0.2.2.dist-info/METADATA
pagic-0.2.2.dist-info/RECORD
