Metadata-Version: 2.1
Name: pagic
Version: 0.2.2
Summary: Top-level package for Pagic.
Home-page: https://github.com/abilian/pagic
Author: Abilian SAS
Author-email: sf@abilian.com
Requires-Python: >=3.9,<4
Classifier: Development Status :: 2 - Pre-Alpha
Classifier: Intended Audience :: Developers
Classifier: Natural Language :: English
Classifier: Programming Language :: Python :: 3
Classifier: Programming Language :: Python :: 3.10
Classifier: Programming Language :: Python :: 3.8
Classifier: Programming Language :: Python :: 3.9
Requires-Dist: Flask (>=2.0.2,<3.0.0)
Requires-Dist: cryptography (>=37.0.2,<38.0.0)
Requires-Dist: sourcetypes (>=0.0.2,<0.0.3)
